keeb_snakeskin/__init__.py
keeb_snakeskin/default_params.py
keeb_snakeskin/generate_pcb_case.py
keeb_snakeskin/import_svg.py
keeb_snakeskin/snakeskin.py
keeb_snakeskin/tenting_stand.py
keeb_snakeskin/tolerance_tests.py
keeb_snakeskin-1.1.3.dist-info/LICENSE
keeb_snakeskin-1.1.3.dist-info/METADATA
keeb_snakeskin-1.1.3.dist-info/WHEEL
keeb_snakeskin-1.1.3.dist-info/entry_points.txt
keeb_snakeskin-1.1.3.dist-info/top_level.txt
keeb_snakeskin-1.1.3.dist-info/RECORD
