Metadata-Version: 2.2
Name: keeb_snakeskin
Version: 1.1.3
Summary: Automatically generate a 3D printable case and magnetic carrycase for your custom split keyboard PCBs, from just the outline. (Also generates cases for other PCBs.)
Author: BlueDrink9
License:                     GNU AFFERO GENERAL PUBLIC LICENSE
Project-URL: Homepage, https://github.com/BlueDrink9/keeb_snakeskin.git
Project-URL: Documentation, https://github.com/BlueDrink9/keeb_snakeskin?tab=readme-ov-file#configuration
Project-URL: Repository, https://github.com/BlueDrink9/keeb_snakeskin.git
Project-URL: Issues, https://github.com/BlueDrink9/keeb_snakeskin/issues
Keywords: mechanical-keyboard,keyboards,3d-printing,ergonomic-keyboard,build123d
Classifier: Development Status :: 4 - Beta
Classifier: Programming Language :: Python
Classifier: Topic :: Scientific/Engineering
Requires-Python: <3.13,>=3.8
License-File: LICENSE
Requires-Dist: build123d==0.8.0
Requires-Dist: svgpathtools>1
Requires-Dist: pygerber<3.0,>2.0
Requires-Dist: drawsvg
Requires-Dist: cadquery-ocp<7.8
